sharemux/webserver.py
sharemux/static/index.html
sharemux/static/jquery/jquery-min.js
sharemux/static/xterm/xterm.css
sharemux/static/xterm/xterm.js
sharemux/static/xterm/xterm.js.map
sharemux-0.3.0.dist-info/LICENSE
sharemux-0.3.0.dist-info/METADATA
sharemux-0.3.0.dist-info/WHEEL
sharemux-0.3.0.dist-info/entry_points.txt
sharemux-0.3.0.dist-info/top_level.txt
sharemux-0.3.0.dist-info/RECORD
